mlfcrafter-0.1.1.dist-info/METADATA
mlfcrafter-0.1.1.dist-info/WHEEL
mlfcrafter-0.1.1.dist-info/entry_points.txt
mlfcrafter-0.1.1.dist-info/licenses/LICENSE
mlfcrafter/__init__.py
mlfcrafter/crafters/__init__.py
mlfcrafter/crafters/categorical_crafter.py
mlfcrafter/crafters/cleaner_crafter.py
mlfcrafter/crafters/data_ingest_crafter.py
mlfcrafter/crafters/deploy_crafter.py
mlfcrafter/crafters/model_crafter.py
mlfcrafter/crafters/scaler_crafter.py
mlfcrafter/crafters/scorer_crafter.py
mlfcrafter/flow_chain.py
mlfcrafter/utils.py
mlfcrafter-0.1.1.dist-info/RECORD
