Metadata-Version: 2.1
Name: mlfcrafter
Version: 0.1.1
Summary: ML Pipeline Automation Framework - Chain together data processing, model training, and deployment with minimal code
Keywords: machine-learning,pipeline,automation,data-science,ml-ops,automl,scikit-learn,data-processing
Author-Email: Burak Civelek <burakcivelekk61@gmail.com>
Maintainer-Email: Burak Civelek <burakcivelekk61@gmail.com>
License: MIT
Classifier: Development Status :: 4 - Beta
Classifier: Intended Audience :: Developers
Classifier: Intended Audience :: Science/Research
Classifier: License :: OSI Approved :: MIT License
Classifier: Operating System :: OS Independent
Classifier: Programming Language :: Python :: 3
Classifier: Programming Language :: Python :: 3.8
Classifier: Programming Language :: Python :: 3.9
Classifier: Programming Language :: Python :: 3.10
Classifier: Programming Language :: Python :: 3.11
Classifier: Programming Language :: Python :: 3.12
Classifier: Topic :: Scientific/Engineering :: Artificial Intelligence
Classifier: Topic :: Software Development :: Libraries :: Python Modules
Classifier: Topic :: System :: Distributed Computing
Project-URL: Homepage, https://github.com/brkcvlk/mlfcrafter
Project-URL: Repository, https://github.com/brkcvlk/mlfcrafter
Project-URL: bug-report, https://github.com/brkcvlk/mlfcrafter/issues
Requires-Python: >=3.9
Requires-Dist: pandas>=2.0.0
Requires-Dist: scikit-learn>=1.3.0
Requires-Dist: numpy>=1.24.0
Requires-Dist: xgboost>=1.7.0
Requires-Dist: joblib>=1.3.0
Provides-Extra: dev
Requires-Dist: pytest>=8.0.0; extra == "dev"
Requires-Dist: pytest-cov>=4.0.0; extra == "dev"
Requires-Dist: pytest-xdist>=3.0.0; extra == "dev"
Requires-Dist: ruff>=0.12.0; extra == "dev"
Requires-Dist: bump2version>=1.0.1; extra == "dev"
Provides-Extra: test
Requires-Dist: pytest>=8.0.0; extra == "test"
Requires-Dist: pytest-cov>=4.0.0; extra == "test"
Provides-Extra: docs
Requires-Dist: mkdocs>=1.6.0; extra == "docs"
Requires-Dist: mkdocs-material>=9.6.0; extra == "docs"
Requires-Dist: mkdocs-gen-files>=0.5.0; extra == "docs"
Requires-Dist: mkdocs-literate-nav>=0.6.0; extra == "docs"
